mysql_connect_automation/__init__.py
mysql_connect_automation/mysql_crud.py
mysqlconnectautomation-0.0.5.dist-info/LICENSE
mysqlconnectautomation-0.0.5.dist-info/METADATA
mysqlconnectautomation-0.0.5.dist-info/WHEEL
mysqlconnectautomation-0.0.5.dist-info/top_level.txt
mysqlconnectautomation-0.0.5.dist-info/RECORD
